odoo/addons/intrastat_product_generic/README.rst
odoo/addons/intrastat_product_generic/__init__.py
odoo/addons/intrastat_product_generic/__manifest__.py
odoo/addons/intrastat_product_generic/i18n/es.po
odoo/addons/intrastat_product_generic/i18n/intrastat_product_generic.pot
odoo/addons/intrastat_product_generic/i18n/sl.po
odoo/addons/intrastat_product_generic/readme/CONTRIBUTORS.rst
odoo/addons/intrastat_product_generic/readme/DESCRIPTION.rst
odoo/addons/intrastat_product_generic/security/intrastat_security.xml
odoo/addons/intrastat_product_generic/static/description/icon.png
odoo/addons/intrastat_product_generic/static/description/index.html
odoo/addons/intrastat_product_generic/views/intrastat_product.xml
odoo12_addon_intrastat_product_generic-12.0.1.0.0.99.dev9.dist-info/METADATA
odoo12_addon_intrastat_product_generic-12.0.1.0.0.99.dev9.dist-info/WHEEL
odoo12_addon_intrastat_product_generic-12.0.1.0.0.99.dev9.dist-info/top_level.txt
odoo12_addon_intrastat_product_generic-12.0.1.0.0.99.dev9.dist-info/RECORD
